django_growl/__init__.py
django_growl/__version__.py
django_growl/apps.py
django_growl/icon.png
django_growl/middleware.py
django_growl/notifier.py
django_growl/management/__init__.py
django_growl/management/commands/__init__.py
django_growl/management/commands/runserver_growl.py
django_growl_notifier-1.0.15.dist-info/licenses/LICENSE
django_growl_notifier-1.0.15.dist-info/METADATA
django_growl_notifier-1.0.15.dist-info/WHEEL
django_growl_notifier-1.0.15.dist-info/top_level.txt
django_growl_notifier-1.0.15.dist-info/RECORD
