Metadata-Version: 2.4
Name: django-growl-notifier
Version: 1.0.15
Summary: Send Django server notifications to Growl
Home-page: https://github.com/cumulus13/django-growl-notifier
Author: Hadi Cahyadi
Author-email: Hadi Cahyadi <cumulus13@gmail.com>
License: MIT
Project-URL: Homepage, https://github.com/cumulus13/django-growl-notifier
Project-URL: Repository, https://github.com/cumulus13/django-growl-notifier
Project-URL: Documentation, https://django-growl-notifier.readthedocs.io
Project-URL: Bug Tracker, https://github.com/cumulus13/django-growl-notifier/issues
Keywords: django,growl,notifications,development
Classifier: Framework :: Django
Classifier: Programming Language :: Python :: 3
Requires-Python: >=3.8
License-File: LICENSE
Requires-Dist: Django>=3.2
Requires-Dist: gntp>=1.0.3
Requires-Dist: version_get
Dynamic: author
Dynamic: home-page
Dynamic: license-file
Dynamic: requires-python
